{
  "title": "Colorful Local Fabric Hanging In The Wind",
  "category": "Indo-Pacific Cultural Documentations & Editorial Scenes",
  "region": "Sumbawa",
  "species": "Cultural Scene",
  "format": "5K RED RAW",
  "nativeFormatBadge": "5K R3D",
  "licenseType": "editorial",
  "pricingTier": "standard",
  "availableSizes": [
    "8K RED RAW",
    "4K ProRes 422 HQ",
    "1080p Master"
  ],
  "camera": "DSMC2 GEMINI 5K S35",
  "behavior": "Natural history sequence documenting colorful local fabric hanging in the wind.",
  "videoUrl": "https://raw.githubusercontent.com/IPFStock/ip-assets-01/main/A032_C097_0917QR_V2-0025.mp4",
  "description": "Close up of colourful sarongs hanging on a line flapping in the wind, Bontoh village, Sangeang island, Sumbawa, Indonesia, No Model Release",
  "keywords": [
    "5k r3d",
    "5k red raw",
    "96 fps",
    "bontoh",
    "bontoh village",
    "close",
    "close up of colourful sarongs hanging on a line flapping in the wind",
    "colorful",
    "colorful local fabric hanging in the wind",
    "colourful",
    "cultural",
    "cultural scene",
    "documentations",
    "dsmc2",
    "dsmc2 gemini 5k s35",
    "editorial",
    "fabric",
    "flapping",
    "gemini",
    "hanging",
    "indo-pacific",
    "indo-pacific cultural documentations editorial scenes",
    "indonesia",
    "island",
    "line",
    "local",
    "model",
    "no model release",
    "r3d",
    "raw",
    "red",
    "redcode"
  ],
  "technicalSpecs": {
    "fileName": "A032_C097_0917QR_V2-0025.mp4",
    "slug": "colorful-local-fabric-hanging-in-the-wind-a032-c097-0917qr-v2-0025",
    "originalCameraCode": "A032_C097_0917QR_V2-0025.mp4",
    "resolution": "5120 x 2700",
    "codec": "r3d",
    "date": "",
    "bitDepth": "16",
    "cameraType": "DSMC2 GEMINI 5K S35",
    "cameraFormat": "REDcode 8:1",
    "fps": "96",
    "aspectRatio": "1.09",
    "duration": "00:00:38:12",
    "sceneCategory": "Culture",
    "family": "",
    "latinName": ""
  },
  "syncSource": "csv"
}