{
  "title": "Whaleshark Swimming Next To Nets With Sunrays",
  "category": "Marine Megafauna, Reptiles & Ocean Mammals",
  "region": "Cenderawasih",
  "species": "Whale Shark",
  "format": "5K RED RAW",
  "nativeFormatBadge": "5K R3D",
  "licenseType": "commercial",
  "pricingTier": "premium",
  "availableSizes": [
    "8K RED RAW",
    "4K ProRes 422 HQ",
    "1080p Master"
  ],
  "camera": "DSMC2 GEMINI 5K S35",
  "behavior": "Natural history sequence documenting whaleshark swimming next to nets with sunrays.",
  "videoUrl": "https://raw.githubusercontent.com/IPFStock/ip-assets-01/main/A004_A008_0412NB_V1-0033.mp4",
  "description": "A whale shark, Rhincodon typus, swims away from the net under a bagan, a traditional drop net fishing boat, Cendrawasih Bay, Papua, Indonesia, Pacific Ocean",
  "keywords": [
    "50 fps",
    "5k r3d",
    "5k red raw",
    "away",
    "bagan",
    "bay",
    "boat",
    "cenderawasih",
    "cendrawasih",
    "cendrawasih bay",
    "drop",
    "dsmc2",
    "dsmc2 gemini 5k s35",
    "fishing",
    "gemini",
    "indonesia",
    "mammals",
    "marine",
    "marine megafauna reptiles ocean mammals",
    "megafauna",
    "net",
    "nets",
    "next",
    "ocean",
    "pacific",
    "pacific ocean",
    "papua",
    "r3d",
    "raw",
    "red",
    "redcode",
    "reptiles"
  ],
  "technicalSpecs": {
    "fileName": "A004_A008_0412NB_V1-0033.mp4",
    "slug": "whaleshark-swimming-next-to-nets-with-sunrays-a004-a008-0412nb-v1-0033",
    "originalCameraCode": "A004_A008_0412NB_V1-0033.mp4",
    "resolution": "5120 x 2700",
    "codec": "r3d",
    "date": "",
    "bitDepth": "16",
    "cameraType": "DSMC2 GEMINI 5K S35",
    "cameraFormat": "REDcode 5:1",
    "fps": "50",
    "aspectRatio": "1.09",
    "duration": "00:02:04:10",
    "sceneCategory": "Underwater",
    "family": "Rhincodontidae (Whale Sharks)",
    "latinName": "Rhincodon typus"
  },
  "syncSource": "csv"
}